{
  "last_updated": "2025-11-25T00:57:06.075042+00:00",
  "stocks": [
    {
      "symbol": "AAPL",
      "price": 275.92,
      "change": 4.43,
      "change_percent": 1.63,
      "previous_close": 271.49
    },
    {
      "symbol": "MSFT",
      "price": 474.0,
      "change": 1.88,
      "change_percent": 0.4,
      "previous_close": 472.12
    },
    {
      "symbol": "AMZN",
      "price": 226.28,
      "change": 5.59,
      "change_percent": 2.53,
      "previous_close": 220.69
    },
    {
      "symbol": "GOOGL",
      "price": 318.58,
      "change": 18.92,
      "change_percent": 6.31,
      "previous_close": 299.66
    },
    {
      "symbol": "NVDA",
      "price": 182.55,
      "change": 3.67,
      "change_percent": 2.05,
      "previous_close": 178.88
    },
    {
      "symbol": "META",
      "price": 613.05,
      "change": 18.8,
      "change_percent": 3.16,
      "previous_close": 594.25
    },
    {
      "symbol": "TSLA",
      "price": 417.78,
      "change": 26.69,
      "change_percent": 6.82,
      "previous_close": 391.09
    },
    {
      "symbol": "BRK-B",
      "price": 507.81,
      "change": 3.77,
      "change_percent": 0.75,
      "previous_close": 504.04
    },
    {
      "symbol": "JPM",
      "price": 298.0,
      "change": -0.02,
      "change_percent": -0.01,
      "previous_close": 298.02
    },
    {
      "symbol": "V",
      "price": 329.3,
      "change": 1.32,
      "change_percent": 0.4,
      "previous_close": 327.98
    },
    {
      "symbol": "MA",
      "price": 537.85,
      "change": -2.55,
      "change_percent": -0.47,
      "previous_close": 540.4
    },
    {
      "symbol": "JNJ",
      "price": 206.05,
      "change": 2.15,
      "change_percent": 1.05,
      "previous_close": 203.9
    },
    {
      "symbol": "UNH",
      "price": 319.05,
      "change": -0.92,
      "change_percent": -0.29,
      "previous_close": 319.97
    },
    {
      "symbol": "XOM",
      "price": 115.97,
      "change": -1.11,
      "change_percent": -0.95,
      "previous_close": 117.08
    },
    {
      "symbol": "WMT",
      "price": 104.06,
      "change": -1.26,
      "change_percent": -1.2,
      "previous_close": 105.32
    },
    {
      "symbol": "PG",
      "price": 146.98,
      "change": -3.94,
      "change_percent": -2.61,
      "previous_close": 150.92
    },
    {
      "symbol": "DIS",
      "price": 101.94,
      "change": -2.34,
      "change_percent": -2.24,
      "previous_close": 104.28
    },
    {
      "symbol": "NFLX",
      "price": 106.97,
      "change": 2.66,
      "change_percent": 2.55,
      "previous_close": 104.31
    },
    {
      "symbol": "TSM",
      "price": 284.64,
      "change": 9.58,
      "change_percent": 3.48,
      "previous_close": 275.06
    },
    {
      "symbol": "BAC",
      "price": 51.93,
      "change": 0.37,
      "change_percent": 0.72,
      "previous_close": 51.56
    }
  ]
}